<annotation>
	<folder />
	<filename>ppe_0672_jpg.rf.ab0ca43b1fb82e9d49d50158ddb3696e.jpg</filename>
	<path>ppe_0672_jpg.rf.ab0ca43b1fb82e9d49d50158ddb3696e.jpg</path>
	<source>
		<database>roboflow.ai</database>
	</source>
	<size>
		<width>224</width>
		<height>224</height>
		<depth>3</depth>
	</size>
	<segmented>0</segmented>
	<object>
		<name>helmet</name>
		<pose>Unspecified</pose>
		<truncated>0</truncated>
		<difficult>0</difficult>
		<occluded>0</occluded>
		<bndbox>
			<xmin>165</xmin>
			<xmax>187</xmax>
			<ymin>52</ymin>
			<ymax>68</ymax>
		</bndbox>
	</object>
	<object>
		<name>person</name>
		<pose>Unspecified</pose>
		<truncated>0</truncated>
		<difficult>0</difficult>
		<occluded>0</occluded>
		<bndbox>
			<xmin>152</xmin>
			<xmax>212</xmax>
			<ymin>48</ymin>
			<ymax>145</ymax>
		</bndbox>
	</object>
</annotation>