<annotation>
	<folder />
	<filename>ppe_0688_jpg.rf.333f51f8b6bbbbbfdc9514012c15ab58.jpg</filename>
	<path>ppe_0688_jpg.rf.333f51f8b6bbbbbfdc9514012c15ab58.jpg</path>
	<source>
		<database>roboflow.ai</database>
	</source>
	<size>
		<width>224</width>
		<height>224</height>
		<depth>3</depth>
	</size>
	<segmented>0</segmented>
	<object>
		<name>helmet</name>
		<pose>Unspecified</pose>
		<truncated>0</truncated>
		<difficult>0</difficult>
		<occluded>0</occluded>
		<bndbox>
			<xmin>135</xmin>
			<xmax>169</xmax>
			<ymin>19</ymin>
			<ymax>63</ymax>
		</bndbox>
	</object>
	<object>
		<name>person</name>
		<pose>Unspecified</pose>
		<truncated>0</truncated>
		<difficult>0</difficult>
		<occluded>0</occluded>
		<bndbox>
			<xmin>111</xmin>
			<xmax>201</xmax>
			<ymin>17</ymin>
			<ymax>224</ymax>
		</bndbox>
	</object>
	<object>
		<name>vest</name>
		<pose>Unspecified</pose>
		<truncated>0</truncated>
		<difficult>0</difficult>
		<occluded>0</occluded>
		<bndbox>
			<xmin>118</xmin>
			<xmax>187</xmax>
			<ymin>99</ymin>
			<ymax>224</ymax>
		</bndbox>
	</object>
</annotation>